is_odd_llm/__init__.py
is_odd_llm/main.py
is_odd_llm/prompt.py
is_odd_llm/response_format.py
is_odd_llm-0.1.0.dist-info/LICENSE
is_odd_llm-0.1.0.dist-info/METADATA
is_odd_llm-0.1.0.dist-info/WHEEL
is_odd_llm-0.1.0.dist-info/top_level.txt
is_odd_llm-0.1.0.dist-info/RECORD
