Metadata-Version: 2.1
Name: is-odd-llm
Version: 0.1.0
Summary: A Python package using LLM to determine if a number is odd
Home-page: https://github.com/yenslife/is-odd-llm
Author: yenslife
Author-email: 77geo5rge6@gmail.com
Classifier: Programming Language :: Python :: 3
Classifier: License :: OSI Approved :: MIT License
License-File: LICENSE
Requires-Dist: openai >=1.40.6
